canonicalize_range.py
canonicalize_range-0.1.0a1.dist-info/licenses/LICENSE
canonicalize_range-0.1.0a1.dist-info/METADATA
canonicalize_range-0.1.0a1.dist-info/WHEEL
canonicalize_range-0.1.0a1.dist-info/top_level.txt
canonicalize_range-0.1.0a1.dist-info/RECORD
