Metadata-Version: 2.4
Name: canonicalize-range
Version: 0.1.0a1
Summary: This Python module provides utilities for normalizing and canonicalizing range objects to ensure they contain complete steps from their start value.
Author-email: Jifeng Wu <jifengwu2k@gmail.com>
License-Expression: MIT
Project-URL: Homepage, https://github.com/jifengwu2k/canonicalize-range
Project-URL: Bug Tracker, https://github.com/jifengwu2k/canonicalize-range/issues
Classifier: Programming Language :: Python :: 2
Classifier: Programming Language :: Python :: 3
Classifier: Operating System :: OS Independent
Requires-Python: >=2
License-File: LICENSE
Dynamic: license-file
